setup.py
ReSession/__init__.py
ReSession/config.py
ReSession/session_base.py
ReSession.egg-info/PKG-INFO
ReSession.egg-info/SOURCES.txt
ReSession.egg-info/dependency_links.txt
ReSession.egg-info/not-zip-safe
ReSession.egg-info/top_level.txt